Metadata-Version: 1.1
Name: git-pr
Version: 0.2.0
Summary: Tool to fetch GitHub pull requests.
Home-page: http://github.com/ikalnytskyi/git-pr/
Author: Ihor Kalnytskyi
Author-email: ihor@kalnytskyi.com
License: MIT
Keywords: git github pull-request
Platform: UNKNOWN
Classifier: Environment :: Console
Classifier: License :: OSI Approved :: MIT License
Classifier: Operating System :: OS Independent
Classifier: Intended Audience :: Developers
Classifier: Intended Audience :: Information Technology
Classifier: Topic :: Terminals
Classifier: Topic :: Software Development
Classifier: Programming Language :: Python
Classifier: Programming Language :: Python :: 2
Classifier: Programming Language :: Python :: 2.7
Classifier: Programming Language :: Python :: 3
Classifier: Programming Language :: Python :: 3.3
Classifier: Programming Language :: Python :: 3.4
Classifier: Programming Language :: Python :: 3.5
